{"version":"4.0.6","xmlns":null,"assembly":"DevExpress.Maui.Gauges","types":[{"name":"RadialProgressBar","type":"DevExpress.Maui.Gauges.RadialProgressBar","doc":null,"attributes":[{"name":"ChildrenReordered","type":"Microsoft.Maui.Controls.VisualElement.EventHandler","isEvent":true},{"name":"Focused","type":"Microsoft.Maui.Controls.VisualElement.EventHandler\u00601","isEvent":true},{"name":"MeasureInvalidated","type":"Microsoft.Maui.Controls.VisualElement.EventHandler","isEvent":true},{"name":"SizeChanged","type":"Microsoft.Maui.Controls.VisualElement.EventHandler","isEvent":true},{"name":"Unfocused","type":"Microsoft.Maui.Controls.VisualElement.EventHandler\u00601","isEvent":true},{"name":"Loaded","type":"Microsoft.Maui.Controls.VisualElement.EventHandler","isEvent":true},{"name":"Unloaded","type":"Microsoft.Maui.Controls.VisualElement.EventHandler","isEvent":true},{"name":"ChildAdded","type":"Microsoft.Maui.Controls.Element.EventHandler\u00601","isEvent":true},{"name":"ChildRemoved","type":"Microsoft.Maui.Controls.Element.EventHandler\u00601","isEvent":true},{"name":"DescendantAdded","type":"Microsoft.Maui.Controls.Element.EventHandler\u00601","isEvent":true},{"name":"DescendantRemoved","type":"Microsoft.Maui.Controls.Element.EventHandler\u00601","isEvent":true},{"name":"ParentChanging","type":"Microsoft.Maui.Controls.Element.EventHandler\u00601","isEvent":true},{"name":"ParentChanged","type":"Microsoft.Maui.Controls.Element.EventHandler","isEvent":true},{"name":"HandlerChanging","type":"Microsoft.Maui.Controls.Element.EventHandler\u00601","isEvent":true},{"name":"HandlerChanged","type":"Microsoft.Maui.Controls.Element.EventHandler","isEvent":true},{"name":"PropertyChanged","type":"Microsoft.Maui.Controls.BindableObject.PropertyChangedEventHandler","isEvent":true},{"name":"PropertyChanging","type":"Microsoft.Maui.Controls.BindableObject.PropertyChangingEventHandler","isEvent":true},{"name":"BindingContextChanged","type":"Microsoft.Maui.Controls.BindableObject.EventHandler","isEvent":true},{"name":"StartValue","type":"DevExpress.Maui.Gauges.RadialProgressBar.StartValue"},{"name":"EndValue","type":"DevExpress.Maui.Gauges.RadialProgressBar.EndValue"},{"name":"StartAngle","type":"DevExpress.Maui.Gauges.RadialProgressBar.StartAngle"},{"name":"SweepAngle","type":"DevExpress.Maui.Gauges.RadialProgressBar.SweepAngle"},{"name":"IsIndeterminate","type":"DevExpress.Maui.Gauges.RadialProgressBar.IsIndeterminate"},{"name":"Value","type":"DevExpress.Maui.Gauges.RadialProgressBar.Value"},{"name":"AnimationDuration","type":"DevExpress.Maui.Gauges.RadialProgressBar.AnimationDuration","values":[{"name":"Zero","type":"System.TimeSpan.Zero"},{"name":"MaxValue","type":"System.TimeSpan.MaxValue"},{"name":"MinValue","type":"System.TimeSpan.MinValue"},{"name":"NanosecondsPerTick","type":"System.TimeSpan.NanosecondsPerTick"},{"name":"TicksPerMicrosecond","type":"System.TimeSpan.TicksPerMicrosecond"},{"name":"TicksPerMillisecond","type":"System.TimeSpan.TicksPerMillisecond"},{"name":"TicksPerSecond","type":"System.TimeSpan.TicksPerSecond"},{"name":"TicksPerMinute","type":"System.TimeSpan.TicksPerMinute"},{"name":"TicksPerHour","type":"System.TimeSpan.TicksPerHour"},{"name":"TicksPerDay","type":"System.TimeSpan.TicksPerDay"}]},{"name":"AnimationEasing","type":"DevExpress.Maui.Gauges.RadialProgressBar.AnimationEasing"},{"name":"Fill","type":"DevExpress.Maui.Gauges.RadialProgressBar.Fill"},{"name":"ValueIndicatorFill","type":"DevExpress.Maui.Gauges.RadialProgressBar.ValueIndicatorFill"},{"name":"Content","type":"DevExpress.Maui.Gauges.RadialProgressBar.Content"},{"name":"ContentTemplate","type":"DevExpress.Maui.Gauges.RadialProgressBar.ContentTemplate"},{"name":"ContentTemplateSelector","type":"DevExpress.Maui.Gauges.RadialProgressBar.ContentTemplateSelector"},{"name":"AllowAnimation","type":"DevExpress.Maui.Gauges.RadialProgressBar.AllowAnimation"},{"name":"Thickness","type":"DevExpress.Maui.Gauges.RadialProgressBar.Thickness"},{"name":"ValueIndicatorThickness","type":"DevExpress.Maui.Gauges.RadialProgressBar.ValueIndicatorThickness"},{"name":"IsClippedToBounds","type":"DevExpress.Maui.Core.DXViewBase.IsClippedToBounds"},{"name":"Padding","type":"DevExpress.Maui.Core.DXViewBase.Padding","values":[{"name":"Zero","type":"Microsoft.Maui.Thickness.Zero"}]},{"name":"BorderThickness","type":"DevExpress.Maui.Core.DXViewBase.BorderThickness","values":[{"name":"Zero","type":"Microsoft.Maui.Thickness.Zero"}]},{"name":"CornerRadius","type":"DevExpress.Maui.Core.DXViewBase.CornerRadius"},{"name":"BorderColor","type":"DevExpress.Maui.Core.DXViewBase.BorderColor"},{"name":"GestureRecognizers","type":"Microsoft.Maui.Controls.View.GestureRecognizers"},{"name":"HorizontalOptions","type":"Microsoft.Maui.Controls.View.HorizontalOptions","values":[{"name":"Start","type":"Microsoft.Maui.Controls.LayoutOptions.Start"},{"name":"Center","type":"Microsoft.Maui.Controls.LayoutOptions.Center"},{"name":"End","type":"Microsoft.Maui.Controls.LayoutOptions.End"},{"name":"Fill","type":"Microsoft.Maui.Controls.LayoutOptions.Fill"},{"name":"StartAndExpand","type":"Microsoft.Maui.Controls.LayoutOptions.StartAndExpand","isObsolete":true},{"name":"CenterAndExpand","type":"Microsoft.Maui.Controls.LayoutOptions.CenterAndExpand","isObsolete":true},{"name":"EndAndExpand","type":"Microsoft.Maui.Controls.LayoutOptions.EndAndExpand","isObsolete":true},{"name":"FillAndExpand","type":"Microsoft.Maui.Controls.LayoutOptions.FillAndExpand","isObsolete":true}]},{"name":"Margin","type":"Microsoft.Maui.Controls.View.Margin","values":[{"name":"Zero","type":"Microsoft.Maui.Thickness.Zero"}]},{"name":"VerticalOptions","type":"Microsoft.Maui.Controls.View.VerticalOptions","values":[{"name":"Start","type":"Microsoft.Maui.Controls.LayoutOptions.Start"},{"name":"Center","type":"Microsoft.Maui.Controls.LayoutOptions.Center"},{"name":"End","type":"Microsoft.Maui.Controls.LayoutOptions.End"},{"name":"Fill","type":"Microsoft.Maui.Controls.LayoutOptions.Fill"},{"name":"StartAndExpand","type":"Microsoft.Maui.Controls.LayoutOptions.StartAndExpand","isObsolete":true},{"name":"CenterAndExpand","type":"Microsoft.Maui.Controls.LayoutOptions.CenterAndExpand","isObsolete":true},{"name":"EndAndExpand","type":"Microsoft.Maui.Controls.LayoutOptions.EndAndExpand","isObsolete":true},{"name":"FillAndExpand","type":"Microsoft.Maui.Controls.LayoutOptions.FillAndExpand","isObsolete":true}]},{"name":"Visual","type":"Microsoft.Maui.Controls.VisualElement.Visual"},{"name":"FlowDirection","type":"Microsoft.Maui.Controls.VisualElement.FlowDirection","values":[{"name":"value__","type":"Microsoft.Maui.FlowDirection.value__"},{"name":"MatchParent","type":"Microsoft.Maui.FlowDirection.MatchParent"},{"name":"LeftToRight","type":"Microsoft.Maui.FlowDirection.LeftToRight"},{"name":"RightToLeft","type":"Microsoft.Maui.FlowDirection.RightToLeft"}]},{"name":"Window","type":"Microsoft.Maui.Controls.VisualElement.Window"},{"name":"AnchorX","type":"Microsoft.Maui.Controls.VisualElement.AnchorX"},{"name":"AnchorY","type":"Microsoft.Maui.Controls.VisualElement.AnchorY"},{"name":"BackgroundColor","type":"Microsoft.Maui.Controls.VisualElement.BackgroundColor"},{"name":"Background","type":"Microsoft.Maui.Controls.VisualElement.Background"},{"name":"Behaviors","type":"Microsoft.Maui.Controls.VisualElement.Behaviors"},{"name":"Bounds","type":"Microsoft.Maui.Controls.VisualElement.Bounds","values":[{"name":"Zero","type":"Microsoft.Maui.Graphics.Rect.Zero"}]},{"name":"Height","type":"Microsoft.Maui.Controls.VisualElement.Height"},{"name":"HeightRequest","type":"Microsoft.Maui.Controls.VisualElement.HeightRequest"},{"name":"InputTransparent","type":"Microsoft.Maui.Controls.VisualElement.InputTransparent"},{"name":"IsEnabled","type":"Microsoft.Maui.Controls.VisualElement.IsEnabled"},{"name":"IsFocused","type":"Microsoft.Maui.Controls.VisualElement.IsFocused"},{"name":"IsVisible","type":"Microsoft.Maui.Controls.VisualElement.IsVisible"},{"name":"MinimumHeightRequest","type":"Microsoft.Maui.Controls.VisualElement.MinimumHeightRequest"},{"name":"MinimumWidthRequest","type":"Microsoft.Maui.Controls.VisualElement.MinimumWidthRequest"},{"name":"MaximumHeightRequest","type":"Microsoft.Maui.Controls.VisualElement.MaximumHeightRequest"},{"name":"MaximumWidthRequest","type":"Microsoft.Maui.Controls.VisualElement.MaximumWidthRequest"},{"name":"Opacity","type":"Microsoft.Maui.Controls.VisualElement.Opacity"},{"name":"Rotation","type":"Microsoft.Maui.Controls.VisualElement.Rotation"},{"name":"RotationX","type":"Microsoft.Maui.Controls.VisualElement.RotationX"},{"name":"RotationY","type":"Microsoft.Maui.Controls.VisualElement.RotationY"},{"name":"Scale","type":"Microsoft.Maui.Controls.VisualElement.Scale"},{"name":"ScaleX","type":"Microsoft.Maui.Controls.VisualElement.ScaleX"},{"name":"ScaleY","type":"Microsoft.Maui.Controls.VisualElement.ScaleY"},{"name":"TranslationX","type":"Microsoft.Maui.Controls.VisualElement.TranslationX"},{"name":"TranslationY","type":"Microsoft.Maui.Controls.VisualElement.TranslationY"},{"name":"Triggers","type":"Microsoft.Maui.Controls.VisualElement.Triggers"},{"name":"Width","type":"Microsoft.Maui.Controls.VisualElement.Width"},{"name":"WidthRequest","type":"Microsoft.Maui.Controls.VisualElement.WidthRequest"},{"name":"X","type":"Microsoft.Maui.Controls.VisualElement.X"},{"name":"Y","type":"Microsoft.Maui.Controls.VisualElement.Y"},{"name":"Clip","type":"Microsoft.Maui.Controls.VisualElement.Clip"},{"name":"Resources","type":"Microsoft.Maui.Controls.VisualElement.Resources"},{"name":"Frame","type":"Microsoft.Maui.Controls.VisualElement.Frame","values":[{"name":"Zero","type":"Microsoft.Maui.Graphics.Rect.Zero"}]},{"name":"Handler","type":"Microsoft.Maui.Controls.VisualElement.Handler"},{"name":"Shadow","type":"Microsoft.Maui.Controls.VisualElement.Shadow"},{"name":"ZIndex","type":"Microsoft.Maui.Controls.VisualElement.ZIndex"},{"name":"DesiredSize","type":"Microsoft.Maui.Controls.VisualElement.DesiredSize","values":[{"name":"Zero","type":"Microsoft.Maui.Graphics.Size.Zero"}]},{"name":"IsLoaded","type":"Microsoft.Maui.Controls.VisualElement.IsLoaded"},{"name":"Navigation","type":"Microsoft.Maui.Controls.NavigableElement.Navigation"},{"name":"Style","type":"Microsoft.Maui.Controls.NavigableElement.Style"},{"name":"StyleClass","type":"Microsoft.Maui.Controls.NavigableElement.StyleClass"},{"name":"class","type":"Microsoft.Maui.Controls.NavigableElement.class"},{"name":"AutomationId","type":"Microsoft.Maui.Controls.Element.AutomationId"},{"name":"ClassId","type":"Microsoft.Maui.Controls.Element.ClassId"},{"name":"Effects","type":"Microsoft.Maui.Controls.Element.Effects"},{"name":"Id","type":"Microsoft.Maui.Controls.Element.Id","values":[{"name":"Empty","type":"System.Guid.Empty"}]},{"name":"StyleId","type":"Microsoft.Maui.Controls.Element.StyleId"},{"name":"Parent","type":"Microsoft.Maui.Controls.Element.Parent"},{"name":"Handler","type":"Microsoft.Maui.Controls.Element.Handler"},{"name":"Dispatcher","type":"Microsoft.Maui.Controls.BindableObject.Dispatcher"},{"name":"BindingContext","type":"Microsoft.Maui.Controls.BindableObject.BindingContext"}]},{"name":"RangeIndicator","type":"DevExpress.Maui.Gauges.RangeIndicator","doc":null,"attributes":[{"name":"CustomDraw","type":"DevExpress.Maui.Gauges.IndicatorBase\u00601.EventHandler\u00601","isEvent":true},{"name":"Loaded","type":"DevExpress.Maui.Core.DXElementBase.EventHandler","isEvent":true},{"name":"Unloaded","type":"DevExpress.Maui.Core.DXElementBase.EventHandler","isEvent":true},{"name":"ChildAdded","type":"Microsoft.Maui.Controls.Element.EventHandler\u00601","isEvent":true},{"name":"ChildRemoved","type":"Microsoft.Maui.Controls.Element.EventHandler\u00601","isEvent":true},{"name":"DescendantAdded","type":"Microsoft.Maui.Controls.Element.EventHandler\u00601","isEvent":true},{"name":"DescendantRemoved","type":"Microsoft.Maui.Controls.Element.EventHandler\u00601","isEvent":true},{"name":"ParentChanging","type":"Microsoft.Maui.Controls.Element.EventHandler\u00601","isEvent":true},{"name":"ParentChanged","type":"Microsoft.Maui.Controls.Element.EventHandler","isEvent":true},{"name":"HandlerChanging","type":"Microsoft.Maui.Controls.Element.EventHandler\u00601","isEvent":true},{"name":"HandlerChanged","type":"Microsoft.Maui.Controls.Element.EventHandler","isEvent":true},{"name":"PropertyChanged","type":"Microsoft.Maui.Controls.BindableObject.PropertyChangedEventHandler","isEvent":true},{"name":"PropertyChanging","type":"Microsoft.Maui.Controls.BindableObject.PropertyChangingEventHandler","isEvent":true},{"name":"BindingContextChanged","type":"Microsoft.Maui.Controls.BindableObject.EventHandler","isEvent":true},{"name":"StartValue","type":"DevExpress.Maui.Gauges.RangeIndicator.StartValue"},{"name":"EndValue","type":"DevExpress.Maui.Gauges.RangeIndicator.EndValue"},{"name":"StartThickness","type":"DevExpress.Maui.Gauges.RangeIndicator.StartThickness"},{"name":"EndThickness","type":"DevExpress.Maui.Gauges.RangeIndicator.EndThickness"},{"name":"StrokeCap","type":"DevExpress.Maui.Gauges.RangeIndicator.StrokeCap","values":[{"name":"value__","type":"SkiaSharp.SKStrokeCap.value__"},{"name":"Butt","type":"SkiaSharp.SKStrokeCap.Butt"},{"name":"Round","type":"SkiaSharp.SKStrokeCap.Round"},{"name":"Square","type":"SkiaSharp.SKStrokeCap.Square"}]},{"name":"Offset","type":"DevExpress.Maui.Gauges.RangeIndicator.Offset"},{"name":"AllowAnimation","type":"DevExpress.Maui.Gauges.IndicatorBase.AllowAnimation"},{"name":"Fill","type":"DevExpress.Maui.Gauges.IndicatorBase.Fill"},{"name":"AnimationEasing","type":"DevExpress.Maui.Gauges.IndicatorBase.AnimationEasing"},{"name":"AnimationDuration","type":"DevExpress.Maui.Gauges.IndicatorBase.AnimationDuration","values":[{"name":"Zero","type":"System.TimeSpan.Zero"},{"name":"MaxValue","type":"System.TimeSpan.MaxValue"},{"name":"MinValue","type":"System.TimeSpan.MinValue"},{"name":"NanosecondsPerTick","type":"System.TimeSpan.NanosecondsPerTick"},{"name":"TicksPerMicrosecond","type":"System.TimeSpan.TicksPerMicrosecond"},{"name":"TicksPerMillisecond","type":"System.TimeSpan.TicksPerMillisecond"},{"name":"TicksPerSecond","type":"System.TimeSpan.TicksPerSecond"},{"name":"TicksPerMinute","type":"System.TimeSpan.TicksPerMinute"},{"name":"TicksPerHour","type":"System.TimeSpan.TicksPerHour"},{"name":"TicksPerDay","type":"System.TimeSpan.TicksPerDay"}]},{"name":"Style","type":"DevExpress.Maui.Core.DXElementBase.Style"},{"name":"IsLoaded","type":"DevExpress.Maui.Core.DXElementBase.IsLoaded"},{"name":"AutomationId","type":"Microsoft.Maui.Controls.Element.AutomationId"},{"name":"ClassId","type":"Microsoft.Maui.Controls.Element.ClassId"},{"name":"Effects","type":"Microsoft.Maui.Controls.Element.Effects"},{"name":"Id","type":"Microsoft.Maui.Controls.Element.Id","values":[{"name":"Empty","type":"System.Guid.Empty"}]},{"name":"StyleId","type":"Microsoft.Maui.Controls.Element.StyleId"},{"name":"Parent","type":"Microsoft.Maui.Controls.Element.Parent"},{"name":"Handler","type":"Microsoft.Maui.Controls.Element.Handler"},{"name":"Dispatcher","type":"Microsoft.Maui.Controls.BindableObject.Dispatcher"},{"name":"BindingContext","type":"Microsoft.Maui.Controls.BindableObject.BindingContext"}]},{"name":"NeedleIndicator","type":"DevExpress.Maui.Gauges.NeedleIndicator","doc":null,"attributes":[{"name":"CustomDraw","type":"DevExpress.Maui.Gauges.IndicatorBase\u00601.EventHandler\u00601","isEvent":true},{"name":"Loaded","type":"DevExpress.Maui.Core.DXElementBase.EventHandler","isEvent":true},{"name":"Unloaded","type":"DevExpress.Maui.Core.DXElementBase.EventHandler","isEvent":true},{"name":"ChildAdded","type":"Microsoft.Maui.Controls.Element.EventHandler\u00601","isEvent":true},{"name":"ChildRemoved","type":"Microsoft.Maui.Controls.Element.EventHandler\u00601","isEvent":true},{"name":"DescendantAdded","type":"Microsoft.Maui.Controls.Element.EventHandler\u00601","isEvent":true},{"name":"DescendantRemoved","type":"Microsoft.Maui.Controls.Element.EventHandler\u00601","isEvent":true},{"name":"ParentChanging","type":"Microsoft.Maui.Controls.Element.EventHandler\u00601","isEvent":true},{"name":"ParentChanged","type":"Microsoft.Maui.Controls.Element.EventHandler","isEvent":true},{"name":"HandlerChanging","type":"Microsoft.Maui.Controls.Element.EventHandler\u00601","isEvent":true},{"name":"HandlerChanged","type":"Microsoft.Maui.Controls.Element.EventHandler","isEvent":true},{"name":"PropertyChanged","type":"Microsoft.Maui.Controls.BindableObject.PropertyChangedEventHandler","isEvent":true},{"name":"PropertyChanging","type":"Microsoft.Maui.Controls.BindableObject.PropertyChangingEventHandler","isEvent":true},{"name":"BindingContextChanged","type":"Microsoft.Maui.Controls.BindableObject.EventHandler","isEvent":true},{"name":"Value","type":"DevExpress.Maui.Gauges.ValueIndicatorBase.Value"},{"name":"StrokeThickness","type":"DevExpress.Maui.Gauges.ValueIndicatorBase.StrokeThickness"},{"name":"Size","type":"DevExpress.Maui.Gauges.ValueIndicatorBase.Size"},{"name":"AllowAnimation","type":"DevExpress.Maui.Gauges.IndicatorBase.AllowAnimation"},{"name":"Fill","type":"DevExpress.Maui.Gauges.IndicatorBase.Fill"},{"name":"AnimationEasing","type":"DevExpress.Maui.Gauges.IndicatorBase.AnimationEasing"},{"name":"AnimationDuration","type":"DevExpress.Maui.Gauges.IndicatorBase.AnimationDuration","values":[{"name":"Zero","type":"System.TimeSpan.Zero"},{"name":"MaxValue","type":"System.TimeSpan.MaxValue"},{"name":"MinValue","type":"System.TimeSpan.MinValue"},{"name":"NanosecondsPerTick","type":"System.TimeSpan.NanosecondsPerTick"},{"name":"TicksPerMicrosecond","type":"System.TimeSpan.TicksPerMicrosecond"},{"name":"TicksPerMillisecond","type":"System.TimeSpan.TicksPerMillisecond"},{"name":"TicksPerSecond","type":"System.TimeSpan.TicksPerSecond"},{"name":"TicksPerMinute","type":"System.TimeSpan.TicksPerMinute"},{"name":"TicksPerHour","type":"System.TimeSpan.TicksPerHour"},{"name":"TicksPerDay","type":"System.TimeSpan.TicksPerDay"}]},{"name":"Style","type":"DevExpress.Maui.Core.DXElementBase.Style"},{"name":"IsLoaded","type":"DevExpress.Maui.Core.DXElementBase.IsLoaded"},{"name":"AutomationId","type":"Microsoft.Maui.Controls.Element.AutomationId"},{"name":"ClassId","type":"Microsoft.Maui.Controls.Element.ClassId"},{"name":"Effects","type":"Microsoft.Maui.Controls.Element.Effects"},{"name":"Id","type":"Microsoft.Maui.Controls.Element.Id","values":[{"name":"Empty","type":"System.Guid.Empty"}]},{"name":"StyleId","type":"Microsoft.Maui.Controls.Element.StyleId"},{"name":"Parent","type":"Microsoft.Maui.Controls.Element.Parent"},{"name":"Handler","type":"Microsoft.Maui.Controls.Element.Handler"},{"name":"Dispatcher","type":"Microsoft.Maui.Controls.BindableObject.Dispatcher"},{"name":"BindingContext","type":"Microsoft.Maui.Controls.BindableObject.BindingContext"}]},{"name":"MarkerIndicator","type":"DevExpress.Maui.Gauges.MarkerIndicator","doc":null,"attributes":[{"name":"CustomDraw","type":"DevExpress.Maui.Gauges.IndicatorBase\u00601.EventHandler\u00601","isEvent":true},{"name":"Loaded","type":"DevExpress.Maui.Core.DXElementBase.EventHandler","isEvent":true},{"name":"Unloaded","type":"DevExpress.Maui.Core.DXElementBase.EventHandler","isEvent":true},{"name":"ChildAdded","type":"Microsoft.Maui.Controls.Element.EventHandler\u00601","isEvent":true},{"name":"ChildRemoved","type":"Microsoft.Maui.Controls.Element.EventHandler\u00601","isEvent":true},{"name":"DescendantAdded","type":"Microsoft.Maui.Controls.Element.EventHandler\u00601","isEvent":true},{"name":"DescendantRemoved","type":"Microsoft.Maui.Controls.Element.EventHandler\u00601","isEvent":true},{"name":"ParentChanging","type":"Microsoft.Maui.Controls.Element.EventHandler\u00601","isEvent":true},{"name":"ParentChanged","type":"Microsoft.Maui.Controls.Element.EventHandler","isEvent":true},{"name":"HandlerChanging","type":"Microsoft.Maui.Controls.Element.EventHandler\u00601","isEvent":true},{"name":"HandlerChanged","type":"Microsoft.Maui.Controls.Element.EventHandler","isEvent":true},{"name":"PropertyChanged","type":"Microsoft.Maui.Controls.BindableObject.PropertyChangedEventHandler","isEvent":true},{"name":"PropertyChanging","type":"Microsoft.Maui.Controls.BindableObject.PropertyChangingEventHandler","isEvent":true},{"name":"BindingContextChanged","type":"Microsoft.Maui.Controls.BindableObject.EventHandler","isEvent":true},{"name":"Position","type":"DevExpress.Maui.Gauges.MarkerIndicator.Position","values":[{"name":"value__","type":"DevExpress.Maui.Gauges.RadialScaleElementPosition.value__"},{"name":"Inside","type":"DevExpress.Maui.Gauges.RadialScaleElementPosition.Inside"},{"name":"Outside","type":"DevExpress.Maui.Gauges.RadialScaleElementPosition.Outside"},{"name":"Center","type":"DevExpress.Maui.Gauges.RadialScaleElementPosition.Center"}]},{"name":"Offset","type":"DevExpress.Maui.Gauges.MarkerIndicator.Offset"},{"name":"Value","type":"DevExpress.Maui.Gauges.ValueIndicatorBase.Value"},{"name":"StrokeThickness","type":"DevExpress.Maui.Gauges.ValueIndicatorBase.StrokeThickness"},{"name":"Size","type":"DevExpress.Maui.Gauges.ValueIndicatorBase.Size"},{"name":"AllowAnimation","type":"DevExpress.Maui.Gauges.IndicatorBase.AllowAnimation"},{"name":"Fill","type":"DevExpress.Maui.Gauges.IndicatorBase.Fill"},{"name":"AnimationEasing","type":"DevExpress.Maui.Gauges.IndicatorBase.AnimationEasing"},{"name":"AnimationDuration","type":"DevExpress.Maui.Gauges.IndicatorBase.AnimationDuration","values":[{"name":"Zero","type":"System.TimeSpan.Zero"},{"name":"MaxValue","type":"System.TimeSpan.MaxValue"},{"name":"MinValue","type":"System.TimeSpan.MinValue"},{"name":"NanosecondsPerTick","type":"System.TimeSpan.NanosecondsPerTick"},{"name":"TicksPerMicrosecond","type":"System.TimeSpan.TicksPerMicrosecond"},{"name":"TicksPerMillisecond","type":"System.TimeSpan.TicksPerMillisecond"},{"name":"TicksPerSecond","type":"System.TimeSpan.TicksPerSecond"},{"name":"TicksPerMinute","type":"System.TimeSpan.TicksPerMinute"},{"name":"TicksPerHour","type":"System.TimeSpan.TicksPerHour"},{"name":"TicksPerDay","type":"System.TimeSpan.TicksPerDay"}]},{"name":"Style","type":"DevExpress.Maui.Core.DXElementBase.Style"},{"name":"IsLoaded","type":"DevExpress.Maui.Core.DXElementBase.IsLoaded"},{"name":"AutomationId","type":"Microsoft.Maui.Controls.Element.AutomationId"},{"name":"ClassId","type":"Microsoft.Maui.Controls.Element.ClassId"},{"name":"Effects","type":"Microsoft.Maui.Controls.Element.Effects"},{"name":"Id","type":"Microsoft.Maui.Controls.Element.Id","values":[{"name":"Empty","type":"System.Guid.Empty"}]},{"name":"StyleId","type":"Microsoft.Maui.Controls.Element.StyleId"},{"name":"Parent","type":"Microsoft.Maui.Controls.Element.Parent"},{"name":"Handler","type":"Microsoft.Maui.Controls.Element.Handler"},{"name":"Dispatcher","type":"Microsoft.Maui.Controls.BindableObject.Dispatcher"},{"name":"BindingContext","type":"Microsoft.Maui.Controls.BindableObject.BindingContext"}]},{"name":"RadialGauge","type":"DevExpress.Maui.Gauges.RadialGauge","doc":null,"attributes":[{"name":"ChildrenReordered","type":"Microsoft.Maui.Controls.VisualElement.EventHandler","isEvent":true},{"name":"Focused","type":"Microsoft.Maui.Controls.VisualElement.EventHandler\u00601","isEvent":true},{"name":"MeasureInvalidated","type":"Microsoft.Maui.Controls.VisualElement.EventHandler","isEvent":true},{"name":"SizeChanged","type":"Microsoft.Maui.Controls.VisualElement.EventHandler","isEvent":true},{"name":"Unfocused","type":"Microsoft.Maui.Controls.VisualElement.EventHandler\u00601","isEvent":true},{"name":"Loaded","type":"Microsoft.Maui.Controls.VisualElement.EventHandler","isEvent":true},{"name":"Unloaded","type":"Microsoft.Maui.Controls.VisualElement.EventHandler","isEvent":true},{"name":"ChildAdded","type":"Microsoft.Maui.Controls.Element.EventHandler\u00601","isEvent":true},{"name":"ChildRemoved","type":"Microsoft.Maui.Controls.Element.EventHandler\u00601","isEvent":true},{"name":"DescendantAdded","type":"Microsoft.Maui.Controls.Element.EventHandler\u00601","isEvent":true},{"name":"DescendantRemoved","type":"Microsoft.Maui.Controls.Element.EventHandler\u00601","isEvent":true},{"name":"ParentChanging","type":"Microsoft.Maui.Controls.Element.EventHandler\u00601","isEvent":true},{"name":"ParentChanged","type":"Microsoft.Maui.Controls.Element.EventHandler","isEvent":true},{"name":"HandlerChanging","type":"Microsoft.Maui.Controls.Element.EventHandler\u00601","isEvent":true},{"name":"HandlerChanged","type":"Microsoft.Maui.Controls.Element.EventHandler","isEvent":true},{"name":"PropertyChanged","type":"Microsoft.Maui.Controls.BindableObject.PropertyChangedEventHandler","isEvent":true},{"name":"PropertyChanging","type":"Microsoft.Maui.Controls.BindableObject.PropertyChangingEventHandler","isEvent":true},{"name":"BindingContextChanged","type":"Microsoft.Maui.Controls.BindableObject.EventHandler","isEvent":true},{"name":"Scales","type":"DevExpress.Maui.Gauges.RadialGauge.Scales"},{"name":"Content","type":"DevExpress.Maui.Core.DXBorder.Content"},{"name":"ContentTemplate","type":"DevExpress.Maui.Core.DXBorder.ContentTemplate"},{"name":"ContentTemplateSelector","type":"DevExpress.Maui.Core.DXBorder.ContentTemplateSelector"},{"name":"IsClippedToBounds","type":"DevExpress.Maui.Core.DXViewBase.IsClippedToBounds"},{"name":"Padding","type":"DevExpress.Maui.Core.DXViewBase.Padding","values":[{"name":"Zero","type":"Microsoft.Maui.Thickness.Zero"}]},{"name":"BorderThickness","type":"DevExpress.Maui.Core.DXViewBase.BorderThickness","values":[{"name":"Zero","type":"Microsoft.Maui.Thickness.Zero"}]},{"name":"CornerRadius","type":"DevExpress.Maui.Core.DXViewBase.CornerRadius"},{"name":"BorderColor","type":"DevExpress.Maui.Core.DXViewBase.BorderColor"},{"name":"GestureRecognizers","type":"Microsoft.Maui.Controls.View.GestureRecognizers"},{"name":"HorizontalOptions","type":"Microsoft.Maui.Controls.View.HorizontalOptions","values":[{"name":"Start","type":"Microsoft.Maui.Controls.LayoutOptions.Start"},{"name":"Center","type":"Microsoft.Maui.Controls.LayoutOptions.Center"},{"name":"End","type":"Microsoft.Maui.Controls.LayoutOptions.End"},{"name":"Fill","type":"Microsoft.Maui.Controls.LayoutOptions.Fill"},{"name":"StartAndExpand","type":"Microsoft.Maui.Controls.LayoutOptions.StartAndExpand","isObsolete":true},{"name":"CenterAndExpand","type":"Microsoft.Maui.Controls.LayoutOptions.CenterAndExpand","isObsolete":true},{"name":"EndAndExpand","type":"Microsoft.Maui.Controls.LayoutOptions.EndAndExpand","isObsolete":true},{"name":"FillAndExpand","type":"Microsoft.Maui.Controls.LayoutOptions.FillAndExpand","isObsolete":true}]},{"name":"Margin","type":"Microsoft.Maui.Controls.View.Margin","values":[{"name":"Zero","type":"Microsoft.Maui.Thickness.Zero"}]},{"name":"VerticalOptions","type":"Microsoft.Maui.Controls.View.VerticalOptions","values":[{"name":"Start","type":"Microsoft.Maui.Controls.LayoutOptions.Start"},{"name":"Center","type":"Microsoft.Maui.Controls.LayoutOptions.Center"},{"name":"End","type":"Microsoft.Maui.Controls.LayoutOptions.End"},{"name":"Fill","type":"Microsoft.Maui.Controls.LayoutOptions.Fill"},{"name":"StartAndExpand","type":"Microsoft.Maui.Controls.LayoutOptions.StartAndExpand","isObsolete":true},{"name":"CenterAndExpand","type":"Microsoft.Maui.Controls.LayoutOptions.CenterAndExpand","isObsolete":true},{"name":"EndAndExpand","type":"Microsoft.Maui.Controls.LayoutOptions.EndAndExpand","isObsolete":true},{"name":"FillAndExpand","type":"Microsoft.Maui.Controls.LayoutOptions.FillAndExpand","isObsolete":true}]},{"name":"Visual","type":"Microsoft.Maui.Controls.VisualElement.Visual"},{"name":"FlowDirection","type":"Microsoft.Maui.Controls.VisualElement.FlowDirection","values":[{"name":"value__","type":"Microsoft.Maui.FlowDirection.value__"},{"name":"MatchParent","type":"Microsoft.Maui.FlowDirection.MatchParent"},{"name":"LeftToRight","type":"Microsoft.Maui.FlowDirection.LeftToRight"},{"name":"RightToLeft","type":"Microsoft.Maui.FlowDirection.RightToLeft"}]},{"name":"Window","type":"Microsoft.Maui.Controls.VisualElement.Window"},{"name":"AnchorX","type":"Microsoft.Maui.Controls.VisualElement.AnchorX"},{"name":"AnchorY","type":"Microsoft.Maui.Controls.VisualElement.AnchorY"},{"name":"BackgroundColor","type":"Microsoft.Maui.Controls.VisualElement.BackgroundColor"},{"name":"Background","type":"Microsoft.Maui.Controls.VisualElement.Background"},{"name":"Behaviors","type":"Microsoft.Maui.Controls.VisualElement.Behaviors"},{"name":"Bounds","type":"Microsoft.Maui.Controls.VisualElement.Bounds","values":[{"name":"Zero","type":"Microsoft.Maui.Graphics.Rect.Zero"}]},{"name":"Height","type":"Microsoft.Maui.Controls.VisualElement.Height"},{"name":"HeightRequest","type":"Microsoft.Maui.Controls.VisualElement.HeightRequest"},{"name":"InputTransparent","type":"Microsoft.Maui.Controls.VisualElement.InputTransparent"},{"name":"IsEnabled","type":"Microsoft.Maui.Controls.VisualElement.IsEnabled"},{"name":"IsFocused","type":"Microsoft.Maui.Controls.VisualElement.IsFocused"},{"name":"IsVisible","type":"Microsoft.Maui.Controls.VisualElement.IsVisible"},{"name":"MinimumHeightRequest","type":"Microsoft.Maui.Controls.VisualElement.MinimumHeightRequest"},{"name":"MinimumWidthRequest","type":"Microsoft.Maui.Controls.VisualElement.MinimumWidthRequest"},{"name":"MaximumHeightRequest","type":"Microsoft.Maui.Controls.VisualElement.MaximumHeightRequest"},{"name":"MaximumWidthRequest","type":"Microsoft.Maui.Controls.VisualElement.MaximumWidthRequest"},{"name":"Opacity","type":"Microsoft.Maui.Controls.VisualElement.Opacity"},{"name":"Rotation","type":"Microsoft.Maui.Controls.VisualElement.Rotation"},{"name":"RotationX","type":"Microsoft.Maui.Controls.VisualElement.RotationX"},{"name":"RotationY","type":"Microsoft.Maui.Controls.VisualElement.RotationY"},{"name":"Scale","type":"Microsoft.Maui.Controls.VisualElement.Scale"},{"name":"ScaleX","type":"Microsoft.Maui.Controls.VisualElement.ScaleX"},{"name":"ScaleY","type":"Microsoft.Maui.Controls.VisualElement.ScaleY"},{"name":"TranslationX","type":"Microsoft.Maui.Controls.VisualElement.TranslationX"},{"name":"TranslationY","type":"Microsoft.Maui.Controls.VisualElement.TranslationY"},{"name":"Triggers","type":"Microsoft.Maui.Controls.VisualElement.Triggers"},{"name":"Width","type":"Microsoft.Maui.Controls.VisualElement.Width"},{"name":"WidthRequest","type":"Microsoft.Maui.Controls.VisualElement.WidthRequest"},{"name":"X","type":"Microsoft.Maui.Controls.VisualElement.X"},{"name":"Y","type":"Microsoft.Maui.Controls.VisualElement.Y"},{"name":"Clip","type":"Microsoft.Maui.Controls.VisualElement.Clip"},{"name":"Resources","type":"Microsoft.Maui.Controls.VisualElement.Resources"},{"name":"Frame","type":"Microsoft.Maui.Controls.VisualElement.Frame","values":[{"name":"Zero","type":"Microsoft.Maui.Graphics.Rect.Zero"}]},{"name":"Handler","type":"Microsoft.Maui.Controls.VisualElement.Handler"},{"name":"Shadow","type":"Microsoft.Maui.Controls.VisualElement.Shadow"},{"name":"ZIndex","type":"Microsoft.Maui.Controls.VisualElement.ZIndex"},{"name":"DesiredSize","type":"Microsoft.Maui.Controls.VisualElement.DesiredSize","values":[{"name":"Zero","type":"Microsoft.Maui.Graphics.Size.Zero"}]},{"name":"IsLoaded","type":"Microsoft.Maui.Controls.VisualElement.IsLoaded"},{"name":"Navigation","type":"Microsoft.Maui.Controls.NavigableElement.Navigation"},{"name":"Style","type":"Microsoft.Maui.Controls.NavigableElement.Style"},{"name":"StyleClass","type":"Microsoft.Maui.Controls.NavigableElement.StyleClass"},{"name":"class","type":"Microsoft.Maui.Controls.NavigableElement.class"},{"name":"AutomationId","type":"Microsoft.Maui.Controls.Element.AutomationId"},{"name":"ClassId","type":"Microsoft.Maui.Controls.Element.ClassId"},{"name":"Effects","type":"Microsoft.Maui.Controls.Element.Effects"},{"name":"Id","type":"Microsoft.Maui.Controls.Element.Id","values":[{"name":"Empty","type":"System.Guid.Empty"}]},{"name":"StyleId","type":"Microsoft.Maui.Controls.Element.StyleId"},{"name":"Parent","type":"Microsoft.Maui.Controls.Element.Parent"},{"name":"Handler","type":"Microsoft.Maui.Controls.Element.Handler"},{"name":"Dispatcher","type":"Microsoft.Maui.Controls.BindableObject.Dispatcher"},{"name":"BindingContext","type":"Microsoft.Maui.Controls.BindableObject.BindingContext"}]},{"name":"RadialScale","type":"DevExpress.Maui.Gauges.RadialScale","doc":null,"attributes":[{"name":"CustomDraw","type":"DevExpress.Maui.Gauges.RadialScale.EventHandler\u00601","isEvent":true},{"name":"CustomizeTickmarkLabel","type":"DevExpress.Maui.Gauges.RadialScale.EventHandler\u00601","isEvent":true},{"name":"CustomizeTickmark","type":"DevExpress.Maui.Gauges.RadialScale.EventHandler\u00601","isEvent":true},{"name":"Loaded","type":"DevExpress.Maui.Core.DXElementBase.EventHandler","isEvent":true},{"name":"Unloaded","type":"DevExpress.Maui.Core.DXElementBase.EventHandler","isEvent":true},{"name":"ChildAdded","type":"Microsoft.Maui.Controls.Element.EventHandler\u00601","isEvent":true},{"name":"ChildRemoved","type":"Microsoft.Maui.Controls.Element.EventHandler\u00601","isEvent":true},{"name":"DescendantAdded","type":"Microsoft.Maui.Controls.Element.EventHandler\u00601","isEvent":true},{"name":"DescendantRemoved","type":"Microsoft.Maui.Controls.Element.EventHandler\u00601","isEvent":true},{"name":"ParentChanging","type":"Microsoft.Maui.Controls.Element.EventHandler\u00601","isEvent":true},{"name":"ParentChanged","type":"Microsoft.Maui.Controls.Element.EventHandler","isEvent":true},{"name":"HandlerChanging","type":"Microsoft.Maui.Controls.Element.EventHandler\u00601","isEvent":true},{"name":"HandlerChanged","type":"Microsoft.Maui.Controls.Element.EventHandler","isEvent":true},{"name":"PropertyChanged","type":"Microsoft.Maui.Controls.BindableObject.PropertyChangedEventHandler","isEvent":true},{"name":"PropertyChanging","type":"Microsoft.Maui.Controls.BindableObject.PropertyChangingEventHandler","isEvent":true},{"name":"BindingContextChanged","type":"Microsoft.Maui.Controls.BindableObject.EventHandler","isEvent":true},{"name":"StartAngle","type":"DevExpress.Maui.Gauges.RadialScale.StartAngle"},{"name":"SweepAngle","type":"DevExpress.Maui.Gauges.RadialScale.SweepAngle"},{"name":"StartValue","type":"DevExpress.Maui.Gauges.RadialScale.StartValue"},{"name":"EndValue","type":"DevExpress.Maui.Gauges.RadialScale.EndValue"},{"name":"MajorTickmarkCount","type":"DevExpress.Maui.Gauges.RadialScale.MajorTickmarkCount"},{"name":"MinorTickmarkCount","type":"DevExpress.Maui.Gauges.RadialScale.MinorTickmarkCount"},{"name":"MajorTickmarkOffset","type":"DevExpress.Maui.Gauges.RadialScale.MajorTickmarkOffset"},{"name":"MinorTickmarkOffset","type":"DevExpress.Maui.Gauges.RadialScale.MinorTickmarkOffset"},{"name":"MajorTickmarkLength","type":"DevExpress.Maui.Gauges.RadialScale.MajorTickmarkLength"},{"name":"MinorTickmarkLength","type":"DevExpress.Maui.Gauges.RadialScale.MinorTickmarkLength"},{"name":"MajorTickmarkThickness","type":"DevExpress.Maui.Gauges.RadialScale.MajorTickmarkThickness"},{"name":"MinorTickmarkThickness","type":"DevExpress.Maui.Gauges.RadialScale.MinorTickmarkThickness"},{"name":"MajorTickmarkColor","type":"DevExpress.Maui.Gauges.RadialScale.MajorTickmarkColor"},{"name":"MinorTickmarkColor","type":"DevExpress.Maui.Gauges.RadialScale.MinorTickmarkColor"},{"name":"MajorTickmarkPosition","type":"DevExpress.Maui.Gauges.RadialScale.MajorTickmarkPosition","values":[{"name":"value__","type":"DevExpress.Maui.Gauges.RadialScaleElementPosition.value__"},{"name":"Inside","type":"DevExpress.Maui.Gauges.RadialScaleElementPosition.Inside"},{"name":"Outside","type":"DevExpress.Maui.Gauges.RadialScaleElementPosition.Outside"},{"name":"Center","type":"DevExpress.Maui.Gauges.RadialScaleElementPosition.Center"}]},{"name":"MinorTickmarkPosition","type":"DevExpress.Maui.Gauges.RadialScale.MinorTickmarkPosition","values":[{"name":"value__","type":"DevExpress.Maui.Gauges.RadialScaleElementPosition.value__"},{"name":"Inside","type":"DevExpress.Maui.Gauges.RadialScaleElementPosition.Inside"},{"name":"Outside","type":"DevExpress.Maui.Gauges.RadialScaleElementPosition.Outside"},{"name":"Center","type":"DevExpress.Maui.Gauges.RadialScaleElementPosition.Center"}]},{"name":"ShowFirstTickmark","type":"DevExpress.Maui.Gauges.RadialScale.ShowFirstTickmark"},{"name":"ShowLastTickmark","type":"DevExpress.Maui.Gauges.RadialScale.ShowLastTickmark"},{"name":"ShowTickmarkLabels","type":"DevExpress.Maui.Gauges.RadialScale.ShowTickmarkLabels"},{"name":"TickmarkLabelOffset","type":"DevExpress.Maui.Gauges.RadialScale.TickmarkLabelOffset"},{"name":"TickmarkLabelFontSize","type":"DevExpress.Maui.Gauges.RadialScale.TickmarkLabelFontSize"},{"name":"TickmarkLabelFormat","type":"DevExpress.Maui.Gauges.RadialScale.TickmarkLabelFormat"},{"name":"TickmarkLabelFontFamily","type":"DevExpress.Maui.Gauges.RadialScale.TickmarkLabelFontFamily"},{"name":"TickmarkLabelColor","type":"DevExpress.Maui.Gauges.RadialScale.TickmarkLabelColor"},{"name":"TickmarkLabelFontAttributes","type":"DevExpress.Maui.Gauges.RadialScale.TickmarkLabelFontAttributes","values":[{"name":"value__","type":"Microsoft.Maui.Controls.FontAttributes.value__"},{"name":"None","type":"Microsoft.Maui.Controls.FontAttributes.None"},{"name":"Bold","type":"Microsoft.Maui.Controls.FontAttributes.Bold"},{"name":"Italic","type":"Microsoft.Maui.Controls.FontAttributes.Italic"}]},{"name":"TickmarkLabelPosition","type":"DevExpress.Maui.Gauges.RadialScale.TickmarkLabelPosition","values":[{"name":"value__","type":"DevExpress.Maui.Gauges.RadialScaleElementPosition.value__"},{"name":"Inside","type":"DevExpress.Maui.Gauges.RadialScaleElementPosition.Inside"},{"name":"Outside","type":"DevExpress.Maui.Gauges.RadialScaleElementPosition.Outside"},{"name":"Center","type":"DevExpress.Maui.Gauges.RadialScaleElementPosition.Center"}]},{"name":"Thickness","type":"DevExpress.Maui.Gauges.RadialScale.Thickness"},{"name":"Offset","type":"DevExpress.Maui.Gauges.RadialScale.Offset"},{"name":"Fill","type":"DevExpress.Maui.Gauges.RadialScale.Fill"},{"name":"StrokeCap","type":"DevExpress.Maui.Gauges.RadialScale.StrokeCap","values":[{"name":"value__","type":"SkiaSharp.SKStrokeCap.value__"},{"name":"Butt","type":"SkiaSharp.SKStrokeCap.Butt"},{"name":"Round","type":"SkiaSharp.SKStrokeCap.Round"},{"name":"Square","type":"SkiaSharp.SKStrokeCap.Square"}]},{"name":"Indicators","type":"DevExpress.Maui.Gauges.RadialScale.Indicators"},{"name":"Style","type":"DevExpress.Maui.Core.DXElementBase.Style"},{"name":"IsLoaded","type":"DevExpress.Maui.Core.DXElementBase.IsLoaded"},{"name":"AutomationId","type":"Microsoft.Maui.Controls.Element.AutomationId"},{"name":"ClassId","type":"Microsoft.Maui.Controls.Element.ClassId"},{"name":"Effects","type":"Microsoft.Maui.Controls.Element.Effects"},{"name":"Id","type":"Microsoft.Maui.Controls.Element.Id","values":[{"name":"Empty","type":"System.Guid.Empty"}]},{"name":"StyleId","type":"Microsoft.Maui.Controls.Element.StyleId"},{"name":"Parent","type":"Microsoft.Maui.Controls.Element.Parent"},{"name":"Handler","type":"Microsoft.Maui.Controls.Element.Handler"},{"name":"Dispatcher","type":"Microsoft.Maui.Controls.BindableObject.Dispatcher"},{"name":"BindingContext","type":"Microsoft.Maui.Controls.BindableObject.BindingContext"}]},{"name":"WaitIndicator","type":"DevExpress.Maui.Gauges.Internal.WaitIndicator","doc":null,"attributes":[{"name":"CustomDraw","type":"DevExpress.Maui.Gauges.IndicatorBase\u00601.EventHandler\u00601","isEvent":true},{"name":"Loaded","type":"DevExpress.Maui.Core.DXElementBase.EventHandler","isEvent":true},{"name":"Unloaded","type":"DevExpress.Maui.Core.DXElementBase.EventHandler","isEvent":true},{"name":"ChildAdded","type":"Microsoft.Maui.Controls.Element.EventHandler\u00601","isEvent":true},{"name":"ChildRemoved","type":"Microsoft.Maui.Controls.Element.EventHandler\u00601","isEvent":true},{"name":"DescendantAdded","type":"Microsoft.Maui.Controls.Element.EventHandler\u00601","isEvent":true},{"name":"DescendantRemoved","type":"Microsoft.Maui.Controls.Element.EventHandler\u00601","isEvent":true},{"name":"ParentChanging","type":"Microsoft.Maui.Controls.Element.EventHandler\u00601","isEvent":true},{"name":"ParentChanged","type":"Microsoft.Maui.Controls.Element.EventHandler","isEvent":true},{"name":"HandlerChanging","type":"Microsoft.Maui.Controls.Element.EventHandler\u00601","isEvent":true},{"name":"HandlerChanged","type":"Microsoft.Maui.Controls.Element.EventHandler","isEvent":true},{"name":"PropertyChanged","type":"Microsoft.Maui.Controls.BindableObject.PropertyChangedEventHandler","isEvent":true},{"name":"PropertyChanging","type":"Microsoft.Maui.Controls.BindableObject.PropertyChangingEventHandler","isEvent":true},{"name":"BindingContextChanged","type":"Microsoft.Maui.Controls.BindableObject.EventHandler","isEvent":true},{"name":"StartValue","type":"DevExpress.Maui.Gauges.RangeIndicator.StartValue"},{"name":"EndValue","type":"DevExpress.Maui.Gauges.RangeIndicator.EndValue"},{"name":"StartThickness","type":"DevExpress.Maui.Gauges.RangeIndicator.StartThickness"},{"name":"EndThickness","type":"DevExpress.Maui.Gauges.RangeIndicator.EndThickness"},{"name":"StrokeCap","type":"DevExpress.Maui.Gauges.RangeIndicator.StrokeCap","values":[{"name":"value__","type":"SkiaSharp.SKStrokeCap.value__"},{"name":"Butt","type":"SkiaSharp.SKStrokeCap.Butt"},{"name":"Round","type":"SkiaSharp.SKStrokeCap.Round"},{"name":"Square","type":"SkiaSharp.SKStrokeCap.Square"}]},{"name":"Offset","type":"DevExpress.Maui.Gauges.RangeIndicator.Offset"},{"name":"AllowAnimation","type":"DevExpress.Maui.Gauges.IndicatorBase.AllowAnimation"},{"name":"Fill","type":"DevExpress.Maui.Gauges.IndicatorBase.Fill"},{"name":"AnimationEasing","type":"DevExpress.Maui.Gauges.IndicatorBase.AnimationEasing"},{"name":"AnimationDuration","type":"DevExpress.Maui.Gauges.IndicatorBase.AnimationDuration","values":[{"name":"Zero","type":"System.TimeSpan.Zero"},{"name":"MaxValue","type":"System.TimeSpan.MaxValue"},{"name":"MinValue","type":"System.TimeSpan.MinValue"},{"name":"NanosecondsPerTick","type":"System.TimeSpan.NanosecondsPerTick"},{"name":"TicksPerMicrosecond","type":"System.TimeSpan.TicksPerMicrosecond"},{"name":"TicksPerMillisecond","type":"System.TimeSpan.TicksPerMillisecond"},{"name":"TicksPerSecond","type":"System.TimeSpan.TicksPerSecond"},{"name":"TicksPerMinute","type":"System.TimeSpan.TicksPerMinute"},{"name":"TicksPerHour","type":"System.TimeSpan.TicksPerHour"},{"name":"TicksPerDay","type":"System.TimeSpan.TicksPerDay"}]},{"name":"Style","type":"DevExpress.Maui.Core.DXElementBase.Style"},{"name":"IsLoaded","type":"DevExpress.Maui.Core.DXElementBase.IsLoaded"},{"name":"AutomationId","type":"Microsoft.Maui.Controls.Element.AutomationId"},{"name":"ClassId","type":"Microsoft.Maui.Controls.Element.ClassId"},{"name":"Effects","type":"Microsoft.Maui.Controls.Element.Effects"},{"name":"Id","type":"Microsoft.Maui.Controls.Element.Id","values":[{"name":"Empty","type":"System.Guid.Empty"}]},{"name":"StyleId","type":"Microsoft.Maui.Controls.Element.StyleId"},{"name":"Parent","type":"Microsoft.Maui.Controls.Element.Parent"},{"name":"Handler","type":"Microsoft.Maui.Controls.Element.Handler"},{"name":"Dispatcher","type":"Microsoft.Maui.Controls.BindableObject.Dispatcher"},{"name":"BindingContext","type":"Microsoft.Maui.Controls.BindableObject.BindingContext"}]}],"timestamp":"05/02/2024 17:07:31","target":"e:\\eProjectsOnRealm-Base -1\\bin\\Debug\\net8.0-ios\\iossimulator-x64"}
